{
  "market": {
    "sp500_futures_pct": 0.75,
    "treasury_10y": 4.493,
    "treasury_10y_change_bps": -6.5,
    "eps_beat_rate": 10
  },
  "note": {
    "market_overview": "S&P 500期货上涨0.75%，10年期美债收益率为4.493%，下降6.5个基点。市场显示小盘股相对大盘股轮动的信号，小盘公司受益于利率下降和财政刺激政策支持，呈现更强增长势头。",
    "macro": "美联储政策环境持续支持，利率环境改善。基础设施支出增加刺激半导体、能源和工业需求。地缘政治事件推动实物资产配置，大宗商品和能源板块受欢迎。小盘股估值相对大盘股折价，吸引力上升。",
    "earnings": "当前财报季医疗保健板块EPS超预期幅度为13%，远高于市场整体7%。半导体产业预期5年年均增长26%，远超历史增长率3.3%。科技板块2026年预期EPS增长5.8%。小盘公司盈利增长加速，缩小与大型科技股的盈利差距。",
    "trade_ideas": "关注小盘/中盘股轮动机会，重点在以下方向：(1)半导体设备和材料供应商，受益于芯片制造景气周期；(2)能源和水处理相关公司，地缘政治支持实物资产配置；(3)医疗和生物科技，财报表现超预期且政策支持；(4)工业和基础设施受益股。避免追高科技大盘股，寻找估值较低、盈利增长确定的中小盘标的。"
  },
  "stock_picks": [
    {
      "ticker": "ACMR",
      "name": "ACM Research Inc.",
      "sector": "半导体",
      "direction": "watch",
      "buy_zone": "$25-28",
      "target": "$35-38",
      "stop_loss": "$22",
      "reason": "半导体清洗设备制造商，受益于芯片制造产能扩张。尽管Q3营收同比增32%，但EPS表现低于预期，需观察后续指引改善信号。"
    },
    {
      "ticker": "UCTT",
      "name": "Ultra Clean Holdings Inc.",
      "sector": "半导体",
      "direction": "buy",
      "buy_zone": "$40-44",
      "target": "$58-62",
      "stop_loss": "$36",
      "reason": "半导体制造耗材和工艺工具供应商，分析师预期12个月内盈利增长98%。受益于芯片超级周期，产能周期处于上升阶段。"
    },
    {
      "ticker": "AMBA",
      "name": "Ambarella Inc.",
      "sector": "半导体",
      "direction": "watch",
      "buy_zone": "$18-21",
      "target": "$28-32",
      "stop_loss": "$16",
      "reason": "计算机视觉芯片供应商，AI视觉应用前景广阔。虽然2025年6-9月涨幅超80%，但年底回落，等待更好买点和盈利验证。"
    },
    {
      "ticker": "GRC",
      "name": "Gorman-Rupp Co.",
      "sector": "工业",
      "direction": "buy",
      "buy_zone": "$29-32",
      "target": "$38-42",
      "stop_loss": "$26",
      "reason": "泵类产品制造商，2025年上涨29%，基本面稳健。分析师预期2026年盈利增长13.6%，12个月涨幅预期19%，股息历史连续增长52年。"
    },
    {
      "ticker": "WTTR",
      "name": "Select Water Solutions Inc.",
      "sector": "能源",
      "direction": "buy",
      "buy_zone": "$10-11",
      "target": "$14-15",
      "stop_loss": "$8.50",
      "reason": "油气行业水处理方案供应商，专注二叠纪盆地。预期YoY盈利增长超25%，当前YTD下跌20.7%提供买点机会，地缘政治支持能源投资。"
    },
    {
      "ticker": "CRSP",
      "name": "CRISPR Therapeutics AG",
      "sector": "生物科技",
      "direction": "buy",
      "buy_zone": "$85-92",
      "target": "$120-130",
      "stop_loss": "$78",
      "reason": "基因编辑生物科技公司，CRISPR技术领导者。医疗板块财报超预期率13%，政策支持有利，生物科技M&A活跃，周均一笔交易。"
    },
    {
      "ticker": "PUBM",
      "name": "PubMatic Inc.",
      "sector": "科技",
      "direction": "watch",
      "buy_zone": "$18-20",
      "target": "$26-30",
      "stop_loss": "$16",
      "reason": "数字广告技术平台，AI驱动的发布商变现方案。AI应用范围扩大，但科技板块估值需关注，等待更优入场点。"
    },
    {
      "ticker": "INSG",
      "name": "Inseego Corp.",
      "sector": "科技",
      "direction": "watch",
      "buy_zone": "$8-9",
      "target": "$14-16",
      "stop_loss": "$7",
      "reason": "5G网络硬件及设备管理软件供应商，次世代5G基础设施建设驱动需求增长。小盘股轮动受益，但需观察营收确认情况。"
    },
    {
      "ticker": "WWW",
      "name": "Wolverine World Wide Inc.",
      "sector": "消费可选",
      "direction": "watch",
      "buy_zone": "$9-11",
      "target": "$13.50-15",
      "stop_loss": "$8",
      "reason": "鞋类制造商，拥有Saucony等知名品牌。预期盈利增长29%，当前YTD下跌14%但近30天上涨21%，产品力改善信号出现。"
    },
    {
      "ticker": "PSTL",
      "name": "Postal Realty Trust Inc.",
      "sector": "固收ETF",
      "direction": "buy",
      "buy_zone": "$14-16",
      "target": "$18-20",
      "stop_loss": "$12",
      "reason": "房地产投资信托，预期FFO增长32.8%，现金收益率5.94%，AFFO折价18.5%。利率下降环保REIT表现，流动性和收益兼具。"
    }
  ],
  "date": "2026-05-27",
  "generated_at": "2026-05-27T09:33:00",
  "market_status": "pre-market",
  "api_cost_usd": 0.0218,
  "budget_usd": 5.0,
  "cumulative_cost_usd": 0.2077,
  "avg_daily_cost_usd": 0.0519,
  "estimated_days_left": 92,
  "balance_warning": false
}