{
  "date": "2026-07-09",
  "live": false,
  "connected": true,
  "nav": 1000503.15,
  "cash": 972966.81,
  "positions": [
    {
      "sym": "NBIX",
      "shares": 2.0,
      "avg_fill": 165.7,
      "cur_price": 177.19000244140625,
      "change_pct": 6.93,
      "pnl_usd": 22.98,
      "today_price": 177.19000244140625,
      "slippage_pct": -6.48,
      "sim_price": null,
      "delay_gap_pct": null,
      "target_usd": 0
    },
    {
      "sym": "AU",
      "shares": 5.0,
      "avg_fill": 80.49,
      "cur_price": 79.57499694824219,
      "change_pct": -1.14,
      "pnl_usd": -4.58,
      "today_price": 79.57499694824219,
      "slippage_pct": 1.15,
      "sim_price": null,
      "delay_gap_pct": null,
      "target_usd": 0
    },
    {
      "sym": "AEM",
      "shares": 3.0,
      "avg_fill": 153.33,
      "cur_price": 144.58999633789062,
      "change_pct": -5.7,
      "pnl_usd": -26.22,
      "today_price": 144.58999633789062,
      "slippage_pct": 6.04,
      "sim_price": null,
      "delay_gap_pct": null,
      "target_usd": 0
    },
    {
      "sym": "ONC",
      "shares": 1.0,
      "avg_fill": 280.32,
      "cur_price": 301.19000244140625,
      "change_pct": 7.45,
      "pnl_usd": 20.87,
      "today_price": 301.19000244140625,
      "slippage_pct": -6.93,
      "sim_price": null,
      "delay_gap_pct": null,
      "target_usd": 0
    },
    {
      "sym": "RVMD",
      "shares": 17.0,
      "avg_fill": 186.42,
      "cur_price": 188.82000732421875,
      "change_pct": 1.29,
      "pnl_usd": 40.8,
      "today_price": 188.82000732421875,
      "slippage_pct": -1.27,
      "sim_price": 162.99,
      "delay_gap_pct": 14.38,
      "target_usd": 333.0
    },
    {
      "sym": "QQQ",
      "shares": 8.0,
      "avg_fill": 715.58,
      "cur_price": 709.72998046875,
      "change_pct": -0.82,
      "pnl_usd": -46.8,
      "today_price": 709.72998046875,
      "slippage_pct": 0.82,
      "sim_price": null,
      "delay_gap_pct": null,
      "target_usd": 1000.0
    },
    {
      "sym": "KSPI",
      "shares": 5.0,
      "avg_fill": 88.04,
      "cur_price": 87.20500183105469,
      "change_pct": -0.95,
      "pnl_usd": -4.17,
      "today_price": 87.20500183105469,
      "slippage_pct": 0.96,
      "sim_price": 82.21,
      "delay_gap_pct": 7.09,
      "target_usd": 0
    },
    {
      "sym": "FUTU",
      "shares": 4.0,
      "avg_fill": 94.45,
      "cur_price": 95.69539642333984,
      "change_pct": 1.32,
      "pnl_usd": 4.98,
      "today_price": 95.69539642333984,
      "slippage_pct": -1.3,
      "sim_price": null,
      "delay_gap_pct": null,
      "target_usd": 0
    },
    {
      "sym": "NU",
      "shares": 33.0,
      "avg_fill": 12.61,
      "cur_price": 13.345000267028809,
      "change_pct": 5.83,
      "pnl_usd": 24.26,
      "today_price": 13.345000267028809,
      "slippage_pct": -5.51,
      "sim_price": null,
      "delay_gap_pct": null,
      "target_usd": 0
    },
    {
      "sym": "FFIV",
      "shares": 8.0,
      "avg_fill": 419.0,
      "cur_price": 419.57501220703125,
      "change_pct": 0.14,
      "pnl_usd": 4.6,
      "today_price": 419.57501220703125,
      "slippage_pct": -0.14,
      "sim_price": 394.53,
      "delay_gap_pct": 6.2,
      "target_usd": 333.0
    },
    {
      "sym": "PDD",
      "shares": 5.0,
      "avg_fill": 74.06,
      "cur_price": 84.91000366210938,
      "change_pct": 14.65,
      "pnl_usd": 54.25,
      "today_price": 84.91000366210938,
      "slippage_pct": -12.78,
      "sim_price": null,
      "delay_gap_pct": null,
      "target_usd": 0
    },
    {
      "sym": "DELL",
      "shares": 8.0,
      "avg_fill": 419.83,
      "cur_price": 430.32501220703125,
      "change_pct": 2.5,
      "pnl_usd": 83.96,
      "today_price": 430.32501220703125,
      "slippage_pct": -2.44,
      "sim_price": 411.8,
      "delay_gap_pct": 1.95,
      "target_usd": 333.0
    },
    {
      "sym": "NVDA",
      "shares": 2.0,
      "avg_fill": 196.51,
      "cur_price": 203.92999267578125,
      "change_pct": 3.78,
      "pnl_usd": 14.84,
      "today_price": 203.92999267578125,
      "slippage_pct": -3.64,
      "sim_price": null,
      "delay_gap_pct": null,
      "target_usd": 0
    }
  ],
  "open_orders": 12,
  "note": "",
  "account": "DUQ627583",
  "total_unrealized_pnl": 189.77,
  "updated_at": "2026-07-09 03:50"
}