{
  "date": "2026-07-21",
  "live": false,
  "connected": true,
  "nav": 999775.49,
  "cash": 972569.16,
  "positions": [
    {
      "sym": "TIGO",
      "shares": 50.0,
      "avg_fill": 99.42,
      "cur_price": 98.06999969482422,
      "change_pct": -1.36,
      "pnl_usd": -67.5,
      "today_price": 98.06999969482422,
      "slippage_pct": 1.38,
      "sim_price": 95.74,
      "delay_gap_pct": 3.84,
      "target_usd": 500.0
    },
    {
      "sym": "OKTA",
      "shares": 33.0,
      "avg_fill": 150.03,
      "cur_price": 139.94000244140625,
      "change_pct": -6.73,
      "pnl_usd": -332.97,
      "today_price": 139.94000244140625,
      "slippage_pct": 7.21,
      "sim_price": 139.53,
      "delay_gap_pct": 7.53,
      "target_usd": 500.0
    },
    {
      "sym": "NBIX",
      "shares": 2.0,
      "avg_fill": 165.7,
      "cur_price": 177.4550018310547,
      "change_pct": 7.09,
      "pnl_usd": 23.51,
      "today_price": 177.4550018310547,
      "slippage_pct": -6.62,
      "sim_price": null,
      "delay_gap_pct": null,
      "target_usd": 0
    },
    {
      "sym": "KSPI",
      "shares": 5.0,
      "avg_fill": 88.36,
      "cur_price": 87.87470245361328,
      "change_pct": -0.55,
      "pnl_usd": -2.43,
      "today_price": 87.87470245361328,
      "slippage_pct": 0.55,
      "sim_price": 88.67,
      "delay_gap_pct": -0.35,
      "target_usd": 0
    },
    {
      "sym": "FUTU",
      "shares": 4.0,
      "avg_fill": 94.45,
      "cur_price": null,
      "change_pct": null,
      "pnl_usd": null,
      "today_price": null,
      "slippage_pct": null,
      "sim_price": null,
      "delay_gap_pct": null,
      "target_usd": 0
    },
    {
      "sym": "NU",
      "shares": 31.0,
      "avg_fill": 12.66,
      "cur_price": 14.115300178527832,
      "change_pct": 11.5,
      "pnl_usd": 45.11,
      "today_price": 14.115300178527832,
      "slippage_pct": -10.31,
      "sim_price": null,
      "delay_gap_pct": null,
      "target_usd": 0
    },
    {
      "sym": "AU",
      "shares": 5.0,
      "avg_fill": 80.49,
      "cur_price": 77.40499877929688,
      "change_pct": -3.83,
      "pnl_usd": -15.43,
      "today_price": 77.40499877929688,
      "slippage_pct": 3.99,
      "sim_price": null,
      "delay_gap_pct": null,
      "target_usd": 0
    },
    {
      "sym": "AEM",
      "shares": 3.0,
      "avg_fill": 140.8,
      "cur_price": 139.5,
      "change_pct": -0.92,
      "pnl_usd": -3.9,
      "today_price": 139.5,
      "slippage_pct": 0.93,
      "sim_price": null,
      "delay_gap_pct": null,
      "target_usd": 0
    },
    {
      "sym": "PDD",
      "shares": 5.0,
      "avg_fill": 74.06,
      "cur_price": 85.0250015258789,
      "change_pct": 14.81,
      "pnl_usd": 54.83,
      "today_price": 85.0250015258789,
      "slippage_pct": -12.9,
      "sim_price": null,
      "delay_gap_pct": null,
      "target_usd": 0
    },
    {
      "sym": "ONC",
      "shares": 1.0,
      "avg_fill": 280.32,
      "cur_price": 317.4104919433594,
      "change_pct": 13.23,
      "pnl_usd": 37.09,
      "today_price": 317.4104919433594,
      "slippage_pct": -11.69,
      "sim_price": null,
      "delay_gap_pct": null,
      "target_usd": 0
    },
    {
      "sym": "NVDA",
      "shares": 2.0,
      "avg_fill": 196.51,
      "cur_price": 205.6300048828125,
      "change_pct": 4.64,
      "pnl_usd": 18.24,
      "today_price": 205.6300048828125,
      "slippage_pct": -4.44,
      "sim_price": null,
      "delay_gap_pct": null,
      "target_usd": 0
    },
    {
      "sym": "QQQ",
      "shares": 8.0,
      "avg_fill": 715.58,
      "cur_price": 705.7899780273438,
      "change_pct": -1.37,
      "pnl_usd": -78.32,
      "today_price": 705.7899780273438,
      "slippage_pct": 1.39,
      "sim_price": null,
      "delay_gap_pct": null,
      "target_usd": 1000.0
    }
  ],
  "open_orders": 12,
  "note": "",
  "account": "DUQ627583",
  "total_unrealized_pnl": -321.77,
  "updated_at": "2026-07-21 23:05"
}