{
  "date": "2026-07-08",
  "live": false,
  "connected": true,
  "nav": 1000496.62,
  "cash": 975235.07,
  "positions": [
    {
      "sym": "NBIX",
      "shares": 2.0,
      "avg_fill": 165.7,
      "cur_price": 177.64500427246094,
      "change_pct": 7.21,
      "pnl_usd": 23.89,
      "today_price": 177.64500427246094,
      "slippage_pct": -6.72,
      "sim_price": null,
      "delay_gap_pct": null,
      "target_usd": 0
    },
    {
      "sym": "AU",
      "shares": 5.0,
      "avg_fill": 80.49,
      "cur_price": 81.91999816894531,
      "change_pct": 1.78,
      "pnl_usd": 7.15,
      "today_price": 81.91999816894531,
      "slippage_pct": -1.75,
      "sim_price": null,
      "delay_gap_pct": null,
      "target_usd": 0
    },
    {
      "sym": "AEM",
      "shares": 2.0,
      "avg_fill": 156.33,
      "cur_price": null,
      "change_pct": null,
      "pnl_usd": null,
      "today_price": null,
      "slippage_pct": null,
      "sim_price": null,
      "delay_gap_pct": null,
      "target_usd": 0
    },
    {
      "sym": "ONC",
      "shares": 1.0,
      "avg_fill": 280.32,
      "cur_price": 305.5899963378906,
      "change_pct": 9.01,
      "pnl_usd": 25.27,
      "today_price": 305.5899963378906,
      "slippage_pct": -8.27,
      "sim_price": null,
      "delay_gap_pct": null,
      "target_usd": 0
    },
    {
      "sym": "RVMD",
      "shares": 13.0,
      "avg_fill": 184.93,
      "cur_price": 189.41000366210938,
      "change_pct": 2.42,
      "pnl_usd": 58.24,
      "today_price": 189.41000366210938,
      "slippage_pct": -2.37,
      "sim_price": 162.99,
      "delay_gap_pct": 13.46,
      "target_usd": 250.0
    },
    {
      "sym": "QQQ",
      "shares": 8.0,
      "avg_fill": 715.58,
      "cur_price": 709.0,
      "change_pct": -0.92,
      "pnl_usd": -52.64,
      "today_price": 709.0,
      "slippage_pct": 0.93,
      "sim_price": null,
      "delay_gap_pct": null,
      "target_usd": 1000.0
    },
    {
      "sym": "AMD",
      "shares": 4.0,
      "avg_fill": 522.82,
      "cur_price": 515.14501953125,
      "change_pct": -1.47,
      "pnl_usd": -30.7,
      "today_price": 515.14501953125,
      "slippage_pct": 1.49,
      "sim_price": 537.37,
      "delay_gap_pct": -2.71,
      "target_usd": 250.0
    },
    {
      "sym": "FTNT",
      "shares": 15.0,
      "avg_fill": 157.51,
      "cur_price": 160.125,
      "change_pct": 1.66,
      "pnl_usd": 39.23,
      "today_price": 160.125,
      "slippage_pct": -1.63,
      "sim_price": 151.35,
      "delay_gap_pct": 4.07,
      "target_usd": 250.0
    },
    {
      "sym": "KSPI",
      "shares": 4.0,
      "avg_fill": 87.58,
      "cur_price": 89.98500061035156,
      "change_pct": 2.75,
      "pnl_usd": 9.62,
      "today_price": 89.98500061035156,
      "slippage_pct": -2.67,
      "sim_price": 82.21,
      "delay_gap_pct": 6.53,
      "target_usd": 0
    },
    {
      "sym": "NU",
      "shares": 31.0,
      "avg_fill": 12.55,
      "cur_price": 13.765000343322754,
      "change_pct": 9.68,
      "pnl_usd": 37.67,
      "today_price": 13.765000343322754,
      "slippage_pct": -8.83,
      "sim_price": null,
      "delay_gap_pct": null,
      "target_usd": 0
    },
    {
      "sym": "FFIV",
      "shares": 5.0,
      "avg_fill": 419.68,
      "cur_price": 420.760009765625,
      "change_pct": 0.26,
      "pnl_usd": 5.4,
      "today_price": 420.760009765625,
      "slippage_pct": -0.26,
      "sim_price": 394.53,
      "delay_gap_pct": 6.37,
      "target_usd": 250.0
    },
    {
      "sym": "PDD",
      "shares": 5.0,
      "avg_fill": 74.06,
      "cur_price": 82.25,
      "change_pct": 11.06,
      "pnl_usd": 40.95,
      "today_price": 82.25,
      "slippage_pct": -9.96,
      "sim_price": null,
      "delay_gap_pct": null,
      "target_usd": 0
    },
    {
      "sym": "NVDA",
      "shares": 2.0,
      "avg_fill": 196.51,
      "cur_price": 194.7100067138672,
      "change_pct": -0.92,
      "pnl_usd": -3.6,
      "today_price": 194.7100067138672,
      "slippage_pct": 0.92,
      "sim_price": null,
      "delay_gap_pct": null,
      "target_usd": 0
    }
  ],
  "open_orders": 13,
  "note": "",
  "account": "DUQ627583",
  "total_unrealized_pnl": 160.48,
  "updated_at": "2026-07-08 00:00"
}