{
  "date": "2026-06-08",
  "ticker": "TISI",
  "action": "SELL",
  "current_price": 17.93,
  "report": {
    "market": "完美！现在我拥有了全面的数据。让我编制一份详细的分析报告。\n\n---\n\n## 详细技术分析报告：TISI（Team, Inc.）\n**分析日期：** 2026年6月5日（最后交易日）  \n**行业：** 工业 / 专业商业服务  \n**交易所：** NYQ（纽约证券交易所）\n\n---\n\n### 执行摘要\n\nTISI正在经历**从下降趋势向强劲看涨突破的动态反转**，仅在两个交易日（6月3-5日）内就实现了显著的+10.5%涨幅。该股票已从超卖状况和负动量指标转变为超买领域和正动量指标。这代表了一个**关键拐点**，在下一个交易时段前需要仔细分析。\n\n---\n\n### 价格行为与趋势分析\n\n#### 最近的价格走势\n- **最后收盘价（2026-06-05）：** $17.72\n- **开盘价（2026-06-05）：** $17.70\n- **高点（2026-06-05）：** $18.50\n- **低点（2026-06-05）：** $17.46\n- **成交量（2026-06-05）：** 7,600股（低于平均水平）\n\n#### 过去一个月的关键价格水平\n该股票经历了多个不同阶段：\n1. **5月11日至5月22日：** 从$15.99至$15.84的初期疲软（低位区间整理）\n2. **5月22日至5月28日：** 短暂的稳定尝试（$16.22 - $16.61），恢复失败\n3. **5月29日至6月2日：** 从$15.81至$15.40的急剧下跌（4天内下跌5.3%），触及30天低点\n4. **6月3日至6月5日：** 从$15.40至$17.72的爆炸性反转涨势（仅2天内上涨15.4%），创造30天新高\n\n---\n\n### 移动平均线分析\n\n**50日简单移动平均线（中期趋势）：** $16.50  \n**200日简单移动平均线（长期趋势）：** $15.67\n\n**解读：**\n- $17.72的价格**高于50日简单移动平均线7.4%**，表明该股票已决定性地突破中期阻力\n- 50日简单移动平均线从5月6日的$15.79逐渐上升至6月5日的$16.50，反映上升趋势形成\n- 该股票**高于200日简单移动平均线13.0%**，确认尽管近期出现下跌，长期趋势仍为正面\n- **黄金…",
    "sentiment": "**总体情绪：** **看涨** (评分: 8.2/10)\n**信心度：** 高\n\n## TISI（Team, Inc.）情绪分析报告\n**分析周期：** 2026-06-01至2026-06-08  \n**分析日期：** 2026-06-08\n\n---\n\n### 逐一来源分析\n\n#### 1. **新闻标题（雅虎财经）**\n- **状态：** 在2026-06-01至2026-06-08期间未找到TISI新闻\n- **信号强度：** 沉寂；分析期间机构新闻流缺失。\n- **解读：** 缺乏负面报道在积极零售活动背景下属于中立至温和看涨。无新闻驱动的阻力。\n\n#### 2. **StockTwits消息（零售情绪）**\n- **样本大小：** 30条最新消息（样本充分）\n- **情绪构成：** \n  - 看涨：27条消息（90%）\n  - 看跌：0条消息（0%）\n  - 未标记：3条消息（10%）\n- **信号强度：** **强烈看涨** — 压倒性的积极零售共识，零看跌异议。\n\n**关键看涨催化剂与叙事主题：**\n\n1. **内部人士买入（主要驱动因素）**\n   - CEO Gary L. Hill在2026-06-02以$16.00价格购买了6,250股（总计10万美元）；目前拥有51,687股。\n   - CEO之前在2026-05-21以$16.22价格购买了5,800股（总计9.4万美元）。\n   - 多条StockTwits帖子明确将内部人士买入框架为「对管理层有信心」的强有力信号，表示低估价值在$16以下。\n   - 用户@Swick02表示：「如果管理层在$16以上买入，看起来我应该在$16以下买入…」— 对内部人士行为应用的理性逆向逻辑。\n   - 来自@CEOBuysDisclosures的消息（2026-06-02）和（2026-05-21）通过表格备案透明度获得高信度。\n\n2. **每股收益超预期与强劲第一季度表现**\n   - 收入同比增长8.3%至$2.151亿，超越分析师共识$2.0888亿 — 自2019年以来最高的第一季度收入。\n   - GAAP每股收益-$3.12，同比增长52.80%（损失幅度改善）。\n   - 非GAAP调整后EBITDA增长伴随扩大的利润率。\n   - 第一季度历来是季节性低谷；零售投资者强调即将到来的…",
    "news": "## 综合新闻分析报告：TISI（Team, Inc.）\n**分析日期：2026年6月8日**\n**覆盖期间：2026年6月1-8日**\n\n---\n\n### 执行摘要\n\n本周呈现混合宏观经济环境，重大逆风抵消了一些积极信号。虽然在分析期间未找到TISI的公司特定新闻，但全球市场背景显示了关键的交易主题，可能影响Team, Inc.在工业/专业商业服务部门的运营和财务表现。\n\n---\n\n### 关键全球市场发展（2026年6月1-8日）\n\n#### 1. **市场波动与恐惧指数飙升**\n- **发现：** 华尔街VIX（\"恐惧指数\"）大幅上升，表明投资者焦虑加剧\n- **含义：** 市场风险厌恶情绪盛行，表明对非防守类股票的投资需求下降\n- **对TISI的影响：** 更高波动率通常为工业公司造成逆风，因为在不确定时期投资和业务扩展决策会被推迟\n\n#### 2. **地缘政治风险：伊朗-以色列紧张局势**\n- **发现：** 伊朗-以色列导弹袭击升级，造成全球市场不确定性\n- **时间表：** 冲突似乎最近升级（在2026年6月8日白银价格文章中提及）\n- **含义：**\n  - 能源价格保持波动\n  - 供应链中断可能性，特别是对制造业相关部门\n  - 商品和工业品风险溢价上升\n- **对TISI的影响：** 作为工业/专业商业服务公司，TISI可能面临：\n  - 投入成本通胀（能源、材料）\n  - 公司延迟自由支配支出时客户需求延迟\n  - 潜在供应链约束\n\n#### 3. **消费品通胀压力**\n- **发现：** 多份报告表明鞋类和消费品部门的持续涨价\n- **具体证据：**\n  - 鞋类价格继续上升…",
    "fundamentals": "现在我拥有了Team, Inc.（TISI）的全面数据。让我编制一份详细的基本面分析报告。\n\n---\n\n# 综合基本面分析报告\n## Team, Inc.（TISI）- 纽约证券交易所\n**分析日期：2026年6月8日**\n\n---\n\n## 执行摘要\n\nTeam, Inc.（TISI）是一家在纽约证券交易所上市的工业专业商业服务公司。该公司目前正经历重大财务困境，特征为负利润率、巨大的累积亏损、负权益和沉重的债务负担。然而，该公司维持积极的营运资本，并继续产生约9亿美元的年度运营收入（TTM基础）。\n\n---\n\n## 公司概况\n\n**公司名称：** Team, Inc.  \n**股票代码：** TISI  \n**交易所：** 纽约证券交易所  \n**部门：** 工业  \n**行业：** 专业商业服务  \n**市值：** 8,196万美元  \n**流通股份：** 457万股（截至2026年第一季度）\n\n---\n\n## 财务健康概览 - 严重关切\n\n### 资本结构 - 严重困顿\n\n**股东权益：** -3,940万美元（2026年第一季度）  \n- 该公司**权益为负**，意味着负债超过资产\n- 这代表自2025年第四季度的-2,500万美元以来的恶化\n- 权益已至少在过去2年以上为负\n- **危险信号：** 负权益在会计学上表示资不抵债\n\n**债务分析：**\n- **总债务：** $3.574亿（2026年第一季度）\n- **长期债务：** $3.026亿\n- **流动债务：** $390万\n- **资本租赁义务：** $5,100万（总计）\n- **债务权益比：** 2,318.9倍（由于负权益而数学上极端）\n- **净债务：** $2.937亿\n\n### 盈利能力指标 - 深度负面\n\n**净收入（TTM）：** -$3,715万  \n**利润率：** -3.38%  \n**营业利润率：** -1.57%  \n\n**季度收入…",
    "debate": "**建议**：减持\n\n**基本原理**：这场辩论呈现了对相同财务数据的两种基本不同的解释，但证据权重倾向于谨慎态度，尽管有一些运营改进。\n\n**公牛派最强的观点：**\n- 运营EBITDA已经转为正值（$5,100万TTM），在深度困顿时期之后，代表基础业务现金生成的真正拐点\n- 2026年第一季度收入超过共识并触及多年高点，表明关键终端市场保有需求\n- CEO内部人士买入（在$16-16.22价格下购入19.4万美元）表明管理层对第二季度结果具有前瞻性可见性，并认为风险/回报不对称\n- 技术设置（黄金交叉、MACD交叉、内部人士买入与收益超预期重合）产生正信号的汇聚\n- 数据中心、航空航天和液化天然气部门的行业利好提供工业服务需求的长期结构性支持\n\n**熊派最强的观点（证明是决定性的）：**\n- **权益赤字急剧恶化**：负权益同比恶化61%（从-2,600万美元至-3,940万美元），与公牛派的「临时滞后」理论矛盾。在真正的好转中，一旦运营改善，权益就会稳定；这里在积极EBITDA背景下它在加速下降。\n- **利润率压缩是真实且结构性的**：2026年第一季度的毛利率23.3%代表从2025年第二季度27.4%的410个基点下降。同比比较（2026年第一季度 vs 2025年第一季度）仅显示50个基点改善，但从2025年第二季度开始的趋势明确向下，表明定价权丧失和/或成本通胀未被转嫁。\n- **利息覆盖率危险紧张**：在TTM基础上为1.16倍，TISI的契约缓冲最小。任何EBITDA下降到4,800万至5,000万美元以下都会违反阈值。熊派对宏观逆风（高企VIX、地缘政治风险、资本支出推迟）将压低第二-第三季度EBITDA的预测是可信的。\n- **2026年第二季度运营收入预测过于乐观**：公牛派的基本情形预计+$240万至+$480万操作…",
    "investment_plan": "**建议**：减持\n\n**基本原理**：这场辩论呈现了对相同财务数据的两种基本不同的解释，但证据权重倾向于谨慎态度，尽管有一些运营改进。\n\n**公牛派最强的观点：**\n- 运营EBITDA已经转为正值（$5,100万TTM），在深度困顿时期之后，代表基础业务现金生成的真正拐点\n- 2026年第一季度收入超过共识并触及多年高点，表明关键终端市场保有需求\n- CEO内部人士买入（在$16-16.22价格下购入19.4万美元）表明管理层对第二季度结果具有前瞻性可见性，并认为风险/回报不对称\n- 技术设置（黄金交叉、MACD交叉、内部人士买入与收益超预期重合）产生正信号的汇聚\n- 数据中心、航空航天和液化天然气部门的行业利好提供工业服务需求的长期结构性支持\n\n**熊派最强的观点（证明是决定性的）：**\n- **权益赤字急剧恶化**：负权益同比恶化61%（从-2,600万美元至-3,940万美元），与公牛派的「临时滞后」理论矛盾。在真正的好转中，一旦运营改善，权益就会稳定；这里在积极EBITDA背景下它在加速下降。\n- **利润率压缩是真实且结构性的**：2026年第一季度的毛利率23.3%代表从2025年第二季度27.4%的410个基点下降。同比比较（2026年第一季度 vs 2025年第一季度）仅显示50个基点改善，但从2025年第二季度开始的趋势明确向下，表明定价权丧失和/或成本通胀未被转嫁。\n- **利息覆盖率危险紧张**：在TTM基础上为1.16倍，TISI的契约缓冲最小。任何EBITDA下降到4,800万至5,000万美元以下都会违反阈值。熊派对宏观逆风（高企VIX、地缘政治风险、资本支出推迟）将压低第二-第三季度EBITDA的预测是可信的。\n- **2026年第二季度运营收入预测过于乐观**：公牛派的基本情形预计+$240万至+$480万操作…",
    "trader_plan": "**行动**：卖出\n\n**理由**：投资计划确立了对TISI当前$17.72价格的明确减持建议，由恶化的基本面支持，这与表面技术设置相悖。权益赤字在改善EBITDA背景下同比恶化61%至-3,940万美元，揭示结构性价值毁灭而非临时「滞后」。毛利率同比压缩410个基点（27.4%至23.3%），利息覆盖率危险紧张在1.16倍，契约缓冲最小。该计划预测至2026年第四季度-2027年第一季度存在60%的违反契约或债务压力概率，迫使30-50%的权益稀释，在12-18个月内驱动股价至$12-16。虽然CEO内部人士买入和技术突破表面上显示强势，但对抵消恶化财务结构和提升重组风险不足。\n\n**入场价格**：18.0\n\n**止损**：15.0\n\n**头寸规模**：减持到最多投资组合的0-2%；不要启动新的多头敞口\n\n最终交易建议：**卖出**",
    "risk": "**评级**：减持\n\n**执行摘要**：TISI尽管运营改进但呈现不可接受的尾部风险：负权益同比恶化61%至-3,940万美元，毛利率同比压缩410个基点（27.4%至23.3%），利息覆盖率危险紧张在1.16倍且存在违反契约风险（60%概率）至2026年第四季度-2027年第一季度。将现有头寸减持到最多0-1%并设置硬性止损在$16.00。不要启动新头寸。6月3-5日的技术涨势（从73K股份崩跌至7.6K成交量）显示疲劳，非机构确信。2026年第二季度收益（6-8周）是关键催化剂；仅运营超预期（收入>$2.3亿、毛利率>24%）才能证明升级至持有。当前$17.72价格反映困顿情绪缓解，非基本面重新定价。\n\n**投资论题**：风险分析员辩论揭示了对相同恶化财务状况的三种竞争解释。激进分析员正确指出$5,100万的积极EBITDA代表真实的现金生成，而负权益单独不保证重组。然而，这忽略了严重的结构性损伤：在支付$4,400万年度利息后，仅剩$700万覆盖折旧（$3,200万至$3,400万）、资本支出、税款和营运资本 — 使公司在维持基础上操作上资不抵债。保守分析员正确指出负权益在过去12个月中恶化$1,340万表明活跃价值毁灭（非「临时滞后」），契约压力将在7-9个月内强制重组。中立分析员适当重新平衡概率：25-30%的运营拐点概率（第二季度超预期→稳定→融资延期）足够有意义以保留0.75-1%敞口，但20-25%的被迫稀释概率（60-75%权益毁灭）和10-15%宏观驱动级联风险要求严格头寸上限和明确退出触发。\n\n**支持减持的决定性证据：**\n\n1…",
    "final": "**评级**：减持\n\n**执行摘要**：TISI尽管运营改进但呈现不可接受的尾部风险：负权益同比恶化61%至-3,940万美元，毛利率同比压缩410个基点（27.4%至23.3%），利息覆盖率危险紧张在1.16倍且存在违反契约风险（60%概率）至2026年第四季度-2027年第一季度。将现有头寸减持到最多0-1%并设置硬性止损在$16.00。不要启动新头寸。6月3-5日的技术涨势（从73K股份崩跌至7.6K成交量）显示疲劳，非机构确信。2026年第二季度收益（6-8周）是关键催化剂；仅运营超预期（收入>$2.3亿、毛利率>24%）才能证明升级至持有。当前$17.72价格反映困顿情绪缓解，非基本面重新定价。\n\n**投资论题**：风险分析员辩论揭示了对相同恶化财务状况的三种竞争解释。激进分析员正确指出$5,100万的积极EBITDA代表真实的现金生成，而负权益单独不保证重组。然而，这忽略了严重的结构性损伤：在支付$4,400万年度利息后，仅剩$700万覆盖折旧（$3,200万至$3,400万）、资本支出、税款和营运资本 — 使公司在维持基础上操作上资不抵债。保守分析员正确指出负权益在过去12个月中恶化$1,340万表明活跃价值毁灭（非「临时滞后」），契约压力将在7-9个月内强制重组。中立分析员适当重新平衡概率：25-30%的运营拐点概率（第二季度超预期→稳定→融资延期）足够有意义以保留0.75-1%敞口，但20-25%的被迫稀释概率（60-75%权益毁灭）和10-15%宏观驱动级联风险要求严格头寸上限和明确退出触发。\n\n**支持减持的决定性证据：**\n\n1…"
  }
}