{
  "date": "2026-07-01",
  "ticker": "SBFG",
  "action": "HOLD",
  "current_price": 25.27,
  "report": {
    "market": "完美！现在我拥有提供全面分析所需的所有数据。让我编制详细报告：\n\n---\n\n## **SBFG（SB Financial Group, Inc.）- 技术分析报告**\n**分析日期：** 2026年7月1日 | **上次交易收盘：** 2026年6月30日\n\n### **执行摘要**\n\nSBFG在2026年6月26日突破后经历**强劲看涨动能阶段**。该股从$21.03（6月3日低点）反弹至**$25.27**（6月30日收盘），在短短四周内上涨**20.2%**。然而，**严重超买信号**现在在多个指标中闪现，表示近期存在拉回或整合风险。\n\n---\n\n### **1. 趋势分析：强劲上升趋势伴随超买条件**\n\n**价格行为与移动平均线：**\n- **当前收盘价：** $25.27（截至2026年6月30日）\n- **10日EMA：** $23.86 – 价格**高出短期均线$1.41**，表明看涨动能持续\n- **50日SMA：** $22.22 – 价格**高出中期趋势线$3.05**，确认既定上升趋势\n- **200日SMA：** $21.05 – 价格**高出长期支撑$4.22**，建立稳固的黄金交叉结构（50 SMA > 200 SMA）\n\n**解读：**\n移动平均线的排列（10 EMA > 50 SMA > 200 SMA）形成教科书式看涨结构。10日EMA位于价格下方，充当动态支撑，而50日SMA作为中间支撑水平。这种分层结构是健康上升趋势的标志。然而，价格远高于所有三条均线的事实表明该走势可能已超出典型整合水平。\n\n---\n\n### **2. 动能分析：超买RSI伴随加速MACD**\n\n**RSI（相对强度指数）：**\n- **当前RSI：** 70.47 – **处于超买区间**（阈值 = 70）\n- **近期轨迹：** 从65.89（6月29日）上升至70.47（6月30日）\n- **历史背景：** RSI从6月1日至5日期间徘徊在42-62区间，表示动能稳定…",
    "sentiment": "**整体情绪：** **温和看涨**（得分：5.8/10）\n**置信度：** 中等\n\n## 逐项来源分析\n\n### 新闻（雅虎财经，过去7天）\n分析窗口内发布了两篇Zacks文章（2026-06-24至2026-07-01）：\n\n1. **\"SB Financial Group (SBFG)上涨5.6%：这种强势能持续吗？\"** — 报告最近股价上涨5.6%，交易量高于平均。然而，标题的限定词（\"这种强势能持续吗？\"）和文章正文指出\"股票的盈利估计修订并不暗示进一步上涨。\"这表明机构谨慎：该走势得到认可，但前景未获分析师修订支持。\n\n2. **\"您在寻找高增长股息股票吗？\"** — 框架为对股息投资者的筛选问题。无明确正面或负面判断；这是可能被广泛受众辛迪加的促销/教育内容。中立框架。\n\n**新闻情绪：谨慎中立至温和看跌。** 价格走势真实，但机构观点（通过分析师修订）不支持看涨延续。\n\n---\n\n### StockTwits（30条最近消息，跨越2024-2026）\n**标记情绪：**\n- 看涨：1条消息（3%）\n- 看跌：0条消息（0%）\n- 未标记：29条消息（97%）\n\n**关键信号：**\n\n- **近期活动（2026年6月）：** 最近消息集中于6月26-12日。一位用户(@Shlobby，6月26日)指出\"$SBFG财务股不多进入我的扫描仪但这看起来很好\"（无标签，但正面语调）。另一位(@focafoca99，6月26日)提供事实信息：2026年第二季度盈利预期7月23日，电话会议7月24日。第三位(@FibonacciTrader_，6月26日)将SBFG列在盘后涨幅中，无明确评论。\n\n- **早期看涨信号（2025春夏）：** \n  - 2026年第一季度盈利（4月24日）显示强劲指标：净收入同比增长99.1%，稀释每股收益$0.69，净利息收入+12.7%，收入+13.2%。这通过@StocktwitsEarnings发布但吸引n…",
    "news": "---\n\n## **综合市场和宏观经济分析**\n### **分析日期：2026年7月1日**\n\n---\n\n## **执行摘要**\n\n截至2026年7月1日，美国经济和金融市场反映**温和限制性货币政策环境，伴随新兴通缩压力和持续平坦的收益率曲线**。SBFG（SB Financial Group, Inc.），一家地区性银行，在以下特征的环境中交易：\n\n- **利率稳定但较高**：联邦基金利率为3.63%，较一年前的4.33%下降70个基点\n- **收益率曲线平坦化**：10-2差价已压缩至仅0.30%，较一年前的0.48%下降，限制了地区性银行净利息边际扩张\n- **核心通胀仍然粘性**：核心PCE同比增长2.89%；CPI标题同比增长3.67%，表明通胀压力尽管降息仍然存在\n- **劳动力市场稳定但非紧张**：失业率4.3%，较一年前持平；无显著劳动力驱动的通胀催化剂\n- **最小衰退风险（12%概率）**和**2026年无美联储降息概率78%**根据预测市场，表明市场预期\"长期高利率\"制度\n\n---\n\n## **一、宏观条件：更广泛的背景**\n\n### **A. 货币政策：降息已暂停**\n\n| 指标 | 最新 | 一年前 | 变化 | 含义 |\n| --- | --- | --- | --- | --- |\n| **联邦基金利率** | 3.63% | 4.33% | -70基点 | 宽松周期完成；进一步降息不太可能 |\n| **10年期美债收益率** | 4.38% | 4.26% | +12基点 | 利率保持粘性；长期债券吸引力较低 |\n| **收益率曲线（10-2）** | 0.30% | 0.48% | -18基点 | 平坦化 = 银行边际压缩 |\n\n**关键洞察**：美联储在2025年7月至2026年5月间降息70个基点，但随后暂停。预测市场表明**2026年无降息概率78%**——表明宽松周期已完成，美联储处于\"保持\"模式。这是SBFG的严重逆风…",
    "fundamentals": "优秀！我现在拥有SBFG的全面财务数据。让我编制详细的基本面分析报告。\n\n---\n\n# 综合基本面分析报告\n## SB Financial Group, Inc. (SBFG)\n**分析日期：** 2026年7月1日  \n**业务分类：** 金融服务/银行 - 地区性  \n**交易所：** NCM（纳斯达克资本市场）\n\n---\n\n## 执行摘要\n\nSB Financial Group, Inc. 是一家以俄亥俄州为总部的地区性银行，为中小型企业和个人提供服务。截至2026年7月1日，该公司展现中等财务健康状况，具有合理的盈利指标、保守的杠杆率和稳定的运营表现。该股交易价格合理的估值和有吸引力的股息收益率，尽管近期现金流波动值得关注。\n\n---\n\n## 公司概况与市场地位\n\n**市值：** $158.6百万  \n**流通股数：** 约630万股（扣除库存股）  \n**当前股价范围：** 52周低$18.16至高$25.60  \n**50日均价：** $22.23  \n**200日均价：** $21.28  \n\nSB Financial Group作为地区性银行运营，在竞争激烈的金融服务部门中运营。公司适度的市值将其置于小盘股银行类别，典型于专注于地方市场而非全国运营的社区和地区性银行。\n\n---\n\n## 关键估值指标\n\n| 指标 | 数值 | 评估 |\n|--------|-------|-----------|\n| **市盈率（TTM）** | 9.91倍 | 低于市场平均（标普500约18-20倍）；表明低估 |\n| **前瞻市盈率** | 9.79倍 | 略低于TTM，表明适度盈利增长 |\n| **市净率** | 1.11倍 | 交易接近账面价值；保守估值 |\n| **股息收益率** | 2.52% | 高于美债收益率；有吸引力的收入部分 |\n| **每股账面价值** | $22.86 | 当前价格~$22.86表明接近账面价值交易 |\n| **贝塔系数** | 0.211 | 极低波动性；高度防守型股票 |\n\n**估值评估：** …",
    "debate": "**建议**：持有\n\n**理由**：这场辩论反映了技术面和基本面叙述之间的真实断裂，双方都呈现连贯——但相反——关于SBFG盈利质量、现金流动态和前瞻盈利可持续性的解释。\n\n**多头最强势的观点：**\n- 2026年第一季度净收入430万美元确实是数据集中最高的季度盈利，净利息收入同比增长12.7%，总收入增长13%\n- 运营边际扩张至28.8%展示了正在实现的运营杠杆\n- 有形账面价值同比增长13.6%是实质性的，表明真实的资本积累\n- \"长期高利率\"环境确实为可以稳定传统贷款组合边际的可预测性提供\n- 9.91倍市盈率低于地区性银行同行平均值（12-14倍），创造了数值估值折扣\n- 资产负债表强度（$1.283亿现金、下降债务、强劲股权增长）提供了安全边际\n\n**空头最强势的观点：**\n- 2025年第一季度崩跌至220万美元（44%低谷），使95%同比比较在数学上夸大；规范化季度盈利似乎为390-400万美元，而非提升的2026年第一季度水平\n- 尽管净收入430万美元，2026年第一季度运营现金流为负（-300万美元），而2025年第二季度也为负（-360万美元），表明令人担忧的模式而非季节性波动\n- 自由现金流-320万美元加上正面应计收益表明典型于银行信用质量恶化的差异\n- 分析师修订正在下降（根据Zacks），这在第一季度财报后7-8周已足以让修订实现；下降的修订表明前瞻怀疑而非分析师滞后\n- 技术设置（RSI 70.47，价格高出上布林带$0.19，突破后成交量下跌93%）真正疲劳\n- 收益率曲线在0.30%（10-2差价）确实对新发放压缩边际，即使传统组合受到保护\n\n**核心分歧…",
    "investment_plan": "**建议**：持有\n\n**理由**：这场辩论反映了技术面和基本面叙述之间的真实断裂，双方都呈现连贯——但相反——关于SBFG盈利质量、现金流动态和前瞻盈利可持续性的解释。\n\n**多头最强势的观点：**\n- 2026年第一季度净收入430万美元确实是数据集中最高的季度盈利，净利息收入同比增长12.7%，总收入增长13%\n- 运营边际扩张至28.8%展示了正在实现的运营杠杆\n- 有形账面价值同比增长13.6%是实质性的，表明真实的资本积累\n- \"长期高利率\"环境确实为可以稳定传统贷款组合边际的可预测性提供\n- 9.91倍市盈率低于地区性银行同行平均值（12-14倍），创造了数值估值折扣\n- 资产负债表强度（$1.283亿现金、下降债务、强劲股权增长）提供了安全边际\n\n**空头最强势的观点：**\n- 2025年第一季度崩跌至220万美元（44%低谷），使95%同比比较在数学上夸大；规范化季度盈利似乎为390-400万美元，而非提升的2026年第一季度水平\n- 尽管净收入430万美元，2026年第一季度运营现金流为负（-300万美元），而2025年第二季度也为负（-360万美元），表明令人担忧的模式而非季节性波动\n- 自由现金流-320万美元加上正面应计收益表明典型于银行信用质量恶化的差异\n- 分析师修订正在下降（根据Zacks），这在第一季度财报后7-8周已足以让修订实现；下降的修订表明前瞻怀疑而非分析师滞后\n- 技术设置（RSI 70.47，价格高出上布林带$0.19，突破后成交量下跌93%）真正疲劳\n- 收益率曲线在0.30%（10-2差价）确实对新发放压缩边际，即使传统组合受到保护\n\n**核心分歧…",
    "trader_plan": "**行动**：持有\n\n**理由**：投资计划确定了看涨运营动能（2026年第一季度净收入430万美元、12.7%同比净利息收入增长、28.8%运营边际、13.6%有形账面价值增长）和看跌现金流疑虑（2026年第一季度运营现金流为负-300万美元尽管正面应计收益、分析师修订下降和技术疲劳，RSI 70.47）之间的真实断裂。关键差异表明延迟方向信念直到2026年第二季度财报（7月23-24日）提供可持续性确认的理由。当前9.91倍市盈率估值对同行似乎折扣但如果盈利增长被夸大则可能被正确折扣。资产负债表强度（$1.283亿现金、强劲股权增长）和股息安全提供下行支撑，而技术疲劳（突破后成交量崩跌）防止在当前水平有令人信服的买入案例。通过第二季度财报催化剂持有而非在含糊的基本面中承诺资本。\n\n**进场价格**：23.8\n\n**止损**：23.5\n\n**仓位规模**：投资组合最多2-3%；延迟新进场直到$23.80-24.00支撑水平或第二季度财报确认后\n\n最终交易提议：**持有**",
    "risk": "**评级**：持有\n\n**执行摘要**：通过2026年第二季度财报（7月23-24日）维持当前仓位，伴随分阶段进场选择权。仅当尚未持有时在当前水平（$25.27）建立2-3%的起始仓位；在$23.86（10日EMA）整合时建立核心3-4%仓位，其中风险/回报改善显著。在$23.50（10日EMA下方支撑）设定硬止损以封顶下行。延迟信念水平规模（6-8%）直到第二季度财报澄清第一季度95%同比增长是否为可持续基线或峰值季度异常，由非重复项目（准备金反转、季节性因素）驱动。\n\n**投资论题**：SBFG呈现真正混合的风险-回报情景，其中看涨和看跌叙述都包含文件证据。多头案例基于真实运营动能：2026年第一季度净收入430万美元（95%同比增长）、净利息收入同比增长12.7%、运营边际扩张至28.8%和13.6%有形账面价值增长。9.91倍市盈率估值确实代表相对地区性银行同行（交易在12-14倍）20-30%折扣，$1.283亿现金头寸提供资产负债表强度。然而，空头案例确定了激进分析师过于轻率驳斥的合理警告信号：（1）2026年第一季度运营现金流为-300万美元尽管净收入430万美元，$5,480万现金流入为融资驱动而非运营生成，表明流动性管理处于压力而非有机积累；（2）分析师修订在第一季度财报8周后下降，表明卖方已纳入第一季度结果并向*下方*修订——这是对盈利可持续性的前瞻共识怀疑，而非分析师滞后；（3）技术设置显示基础案例是整合至$23.86（10日EMA），概率55%根据技术报告，而非延续。突破后成交量下跌93%从6月26日峰值（88.4万至59-65万），表明机构信念减弱。核心分析差异…",
    "final": "**评级**：持有\n\n**执行摘要**：通过2026年第二季度财报（7月23-24日）维持当前仓位，伴随分阶段进场选择权。仅当尚未持有时在当前水平（$25.27）建立2-3%的起始仓位；在$23.86（10日EMA）整合时建立核心3-4%仓位，其中风险/回报改善显著。在$23.50（10日EMA下方支撑）设定硬止损以封顶下行。延迟信念水平规模（6-8%）直到第二季度财报澄清第一季度95%同比增长是否为可持续基线或峰值季度异常，由非重复项目（准备金反转、季节性因素）驱动。\n\n**投资论题**：SBFG呈现真正混合的风险-回报情景，其中看涨和看跌叙述都包含文件证据。多头案例基于真实运营动能：2026年第一季度净收入430万美元（95%同比增长）、净利息收入同比增长12.7%、运营边际扩张至28.8%和13.6%有形账面价值增长。9.91倍市盈率估值确实代表相对地区性银行同行（交易在12-14倍）20-30%折扣，$1.283亿现金头寸提供资产负债表强度。然而，空头案例确定了激进分析师过于轻率驳斥的合理警告信号：（1）2026年第一季度运营现金流为-300万美元尽管净收入430万美元，$5,480万现金流入为融资驱动而非运营生成，表明流动性管理处于压力而非有机积累；（2）分析师修订在第一季度财报8周后下降，表明卖方已纳入第一季度结果并向*下方*修订——这是对盈利可持续性的前瞻共识怀疑，而非分析师滞后；（3）技术设置显示基础案例是整合至$23.86（10日EMA），概率55%根据技术报告，而非延续。突破后成交量下跌93%从6月26日峰值（88.4万至59-65万），表明机构信念减弱。核心分析差异…"
  }
}